palmmeteo/__init__.py
palmmeteo/__main__.py
palmmeteo/_version.py
palmmeteo/config.py
palmmeteo/config_init.yaml
palmmeteo/dispatch.py
palmmeteo/library.py
palmmeteo/logging.py
palmmeteo/plugins.py
palmmeteo/runtime.py
palmmeteo/utils.py
palmmeteo/vinterp.py
palmmeteo/vinterp_native.f90
palmmeteo_stdplugins/__init__.py
palmmeteo_stdplugins/aladin.py
palmmeteo_stdplugins/cams.py
palmmeteo_stdplugins/camx.py
palmmeteo_stdplugins/config_init.yaml
palmmeteo_stdplugins/icon.py
palmmeteo_stdplugins/meteo.py
palmmeteo_stdplugins/plot.py
palmmeteo_stdplugins/setup.py
palmmeteo_stdplugins/setup_staticdriver.py
palmmeteo_stdplugins/synthetic.py
palmmeteo_stdplugins/winddamp.py
palmmeteo_stdplugins/wrf.py
palmmeteo_stdplugins/wrf_utils.py
palmmeteo_stdplugins/write.py
palmmeteo-2.6.6.dist-info/LICENSE
palmmeteo-2.6.6.dist-info/METADATA
palmmeteo-2.6.6.dist-info/WHEEL
palmmeteo-2.6.6.dist-info/entry_points.txt
palmmeteo-2.6.6.dist-info/top_level.txt
palmmeteo-2.6.6.dist-info/RECORD
