Metadata-Version: 2.1
Name: palmmeteo
Version: 2.6.6
Summary: PALM-meteo: processor of meteorological input data for the PALM model system.
Author-email: Pavel Krc <krc@cs.cas.cz>
License: GPL-3.0-or-later
Project-URL: Homepage, https://github.com/PALM-tools/palmmeteo
Project-URL: Issues, https://github.com/PALM-tools/palmmeteo/issues
Classifier: Programming Language :: Python :: 3
Classifier: Operating System :: POSIX :: Linux
Classifier: Operating System :: Microsoft :: Windows
Classifier: Development Status :: 4 - Beta
Requires-Python: >=3.10
License-File: LICENSE
Requires-Dist: netCDF4 (>=1.7.2)
Requires-Dist: pytest (>=7.0)
Requires-Dist: pyyaml (>=6.0)
Requires-Dist: pyzstd ; python_version < "3.14"
Requires-Dist: numpy (<2.2,>=2.1) ; python_version >= "3.10"
Requires-Dist: pyproj (>=3.7) ; python_version >= "3.10"
Requires-Dist: scipy (>=1.15) ; python_version >= "3.10"
Requires-Dist: pint (>=0.23) ; python_version >= "3.9"
Provides-Extra: aladin
Requires-Dist: cfgrib (>=0.9.10) ; extra == 'aladin'
Requires-Dist: xarray (>=2024.1.0) ; extra == 'aladin'
Provides-Extra: geostrophic_wind
Requires-Dist: metpy (>=1.6) ; extra == 'geostrophic_wind'
Provides-Extra: plot
Requires-Dist: matplotlib (>=3.0) ; extra == 'plot'
Provides-Extra: vinterp_metpy
Requires-Dist: metpy (>=1.6) ; extra == 'vinterp_metpy'
